sageworks_bridges/__init__.py
sageworks_bridges/aws/sagemaker_session.py
sageworks_bridges/endpoints/fast_inference.py
sageworks_bridges-0.1.0.dist-info/LICENSE
sageworks_bridges-0.1.0.dist-info/METADATA
sageworks_bridges-0.1.0.dist-info/WHEEL
sageworks_bridges-0.1.0.dist-info/top_level.txt
sageworks_bridges-0.1.0.dist-info/RECORD
