Metadata-Version: 2.1
Name: sageworks-bridges
Version: 0.1.0
Summary: SageWorks Bridges: End User Application Bridges to SageWorks/AWS
Author-email: SuperCowPowers LLC <support@supercowpowers.com>
License: MIT
Project-URL: Homepage, https://github.com/SuperCowPowers/sageworks-bridges
Keywords: SageMaker,Machine Learning,AWS,Python,Utilities
Classifier: Development Status :: 4 - Beta
Classifier: License :: OSI Approved :: MIT License
Classifier: Programming Language :: Python :: 3.10
Classifier: Programming Language :: Python :: 3.11
Classifier: Programming Language :: Python :: 3.12
Classifier: Topic :: Scientific/Engineering
Requires-Python: >=3.9
License-File: LICENSE
Requires-Dist: boto3>=1.28.76
Requires-Dist: botocore>=1.31.76
Requires-Dist: awswrangler>=3.4.0
Requires-Dist: sagemaker>=2.143
Requires-Dist: requests>=2.26.0
